brainglobe_ccf_translator/PointSet.py
brainglobe_ccf_translator/Volume.py
brainglobe_ccf_translator/VolumeSeries.py
brainglobe_ccf_translator/__init__.py
brainglobe_ccf_translator/read_write.py
brainglobe_ccf_translator/deformation/__init__.py
brainglobe_ccf_translator/deformation/apply_deformation.py
brainglobe_ccf_translator/deformation/forward_transform.py
brainglobe_ccf_translator/deformation/route_calculation.py
brainglobe_ccf_translator/deformation/interpolation/NearestNDInterpolator.py
brainglobe_ccf_translator/deformation/interpolation/__init__.py
brainglobe_ccf_translator/metadata/translation_metadata.csv
brainglobe_ccf_translator-0.21.dist-info/LICENSE
brainglobe_ccf_translator-0.21.dist-info/METADATA
brainglobe_ccf_translator-0.21.dist-info/WHEEL
brainglobe_ccf_translator-0.21.dist-info/top_level.txt
brainglobe_ccf_translator-0.21.dist-info/RECORD
